price2bq_mg/__init__.py
price2bq_mg/main.py
price2bq_mg-1.1.0.dist-info/LICENSE
price2bq_mg-1.1.0.dist-info/METADATA
price2bq_mg-1.1.0.dist-info/WHEEL
price2bq_mg-1.1.0.dist-info/RECORD
