Metadata-Version: 2.1
Name: price2bq-mg
Version: 1.1.0
Summary: Экспорт файлов c площадок 'Яндекс Недвижимость', 'Авито' 'Циан' в BigQuery
Author: viktor
Author-email: vi.dave@yandex.ru
Requires-Python: >=3.10,<3.11
Classifier: Programming Language :: Python :: 3
Classifier: Programming Language :: Python :: 3.10
Requires-Dist: bq-easy-zfullio (>=1,<2)
Requires-Dist: loguru (>=0,<1)
Requires-Dist: openpyxl (>=3,<4)
Requires-Dist: pandas (>=2,<3)
Requires-Dist: python-dotenv (>=1,<2)
Requires-Dist: xlrd (>=2,<3)
